Metadata-Version: 2.1
Name: finformula
Version: 0.0.1
Summary: Testing installation of Package
Home-page: https://git03.hundsun.com/AIQA/aiqa-ie/tree/dev/finformula
Author: Ding
Author-email: dingxuechun@hotmail.com
License: MIT
Platform: UNKNOWN
